{
  "hey_commander": "ようこそ、<span class=\"gfl2-font-bold gfl2-text-primary\">指揮官！</span>",
  "welcome_to_exilium_tracker": "EXILIUM Trackerへようこそ。 ここはドールズフロントライン２：エクシリウムのツールサイトで、訪問履歴とアチーブメントなどの記録は追跡可能です。全世界の訪問統計、複数アカウントの管理、それに違う装置にデータを同期することもできます。",
  "quick_links": "各種リンク",
  "import_data": "インポート",
  "import_data_description": "データをインポートする",
  "pull_history": "訪問履歴",
  "pull_history_description": "訪問履歴を見る",
  "statistics": "訪問統計",
  "statistics_description": "全世界の訪問統計を見る",
  "achievements": "アチーブメント",
  "achievements_description": "アチーブメントを追跡する",
  "event_notices": "イベント",
  "how_to_import": "訪問履歴がインポートしたい",
  "how_to_import_description": "Windows PC、AndroidまたはiOSの装置でインポートできます。それぞれの装置に表示される手順に従ってインポートしてください。",
  "where_is_my_data_stored": "データの保存場所について知りたい",
  "where_is_my_data_stored_description": "すべてのデータはデフォルトであなたのデバイスにローカルで保存されます。クラウド同期を利用する場合、データはあなたの個人のGoogleドライブに保存され、異なるデバイスからアクセスできるようになります。",
  "can_i_track_multiple_accounts": "複数のアカウント記録は追跡したい",
  "can_i_track_multiple_accounts_description": "複数のアカウントを作成して管理することができ、異なるゲーム内アカウントを追跡できます。サイトのアカウントはそれぞれのゲーム内アカウントデータと統計資料を対応します。",
  "footer_copyright": "© {year} EXILIUM Tracker",
  "footer_disclaimer": "このサイトはMICA TeamまたはSunborn Network Technologyとは関係しておらず、承認もされていません。すべてのゲーム内画像、コンテンツ、および商標はそれぞれの所有者に帰属します。",
  "official_links": "公式リンク",
  "official_website_darkwinter": "公式サイト (Darkwinter)",
  "official_website_haoplay": "公式サイト (Haoplay)",
  "social": "SNS",
  "official_discord": "公式Discord",
  "official_reddit": "公式Reddit",
  "legal": "利用規約",
  "server_statistics": "サーバー統計",
  "total_across_all_servers": "全サーバー",
  "users_count": "{count, plural, =0 {人} =1 {人} other {人}}",
  "pulls_count": "{count, plural, =0 {回訪問} =1 {回訪問} other {回訪問}}"
}
